troubadix/__init__.py
troubadix/__version__.py
troubadix/argparser.py
troubadix/codespell/codespell.additions
troubadix/codespell/codespell.exclude
troubadix/codespell/codespell.ignore
troubadix/helper/__init__.py
troubadix/helper/date_format.py
troubadix/helper/helper.py
troubadix/helper/if_block_parser.py
troubadix/helper/linguistic_exception_handler.py
troubadix/helper/patterns.py
troubadix/helper/remove_comments.py
troubadix/helper/text_utils.py
troubadix/plugin.py
troubadix/plugins/__init__.py
troubadix/plugins/badwords.py
troubadix/plugins/copyright_text.py
troubadix/plugins/copyright_year.py
troubadix/plugins/creation_date.py
troubadix/plugins/cve_format.py
troubadix/plugins/cvss_format.py
troubadix/plugins/dependencies.py
troubadix/plugins/dependency_category_order.py
troubadix/plugins/deprecated_dependency.py
troubadix/plugins/deprecated_functions.py
troubadix/plugins/double_end_points.py
troubadix/plugins/duplicate_oid.py
troubadix/plugins/duplicated_script_tags.py
troubadix/plugins/encoding.py
troubadix/plugins/forking_nasl_functions.py
troubadix/plugins/get_kb_on_services.py
troubadix/plugins/grammar.py
troubadix/plugins/http_links_in_tags.py
troubadix/plugins/if_statement_syntax.py
troubadix/plugins/illegal_characters.py
troubadix/plugins/log_messages.py
troubadix/plugins/malformed_dependencies.py
troubadix/plugins/misplaced_compare_in_if.py
troubadix/plugins/missing_desc_exit.py
troubadix/plugins/missing_tag_solution.py
troubadix/plugins/multiple_re_parameters.py
troubadix/plugins/newlines.py
troubadix/plugins/overlong_description_lines.py
troubadix/plugins/overlong_script_tags.py
troubadix/plugins/prod_svc_detect_in_vulnvt.py
troubadix/plugins/qod.py
troubadix/plugins/reporting_consistency.py
troubadix/plugins/script_add_preference_id.py
troubadix/plugins/script_add_preference_type.py
troubadix/plugins/script_calls_empty_values.py
troubadix/plugins/script_calls_recommended.py
troubadix/plugins/script_category.py
troubadix/plugins/script_copyright.py
troubadix-26.1.0.dist-info/METADATA
troubadix-26.1.0.dist-info/WHEEL
troubadix-26.1.0.dist-info/entry_points.txt
troubadix-26.1.0.dist-info/licenses/LICENSE
troubadix-26.1.0.dist-info/RECORD
