Metadata-Version: 2.4
Name: troubadix
Version: 26.1.0
Summary: A linting and QA check tool for NASL files
License: GPL-3.0-or-later
License-File: LICENSE
Author: Greenbone
Author-email: info@greenbone.net
Requires-Python: >=3.10,<4.0
Classifier: Development Status :: 4 - Beta
Classifier: Environment :: Console
Classifier: Intended Audience :: Developers
Classifier: License :: OSI Approved :: GNU General Public License v3 or later (GPLv3+)
Classifier: Operating System :: OS Independent
Classifier: Programming Language :: Python :: 3
Classifier: Programming Language :: Python :: 3.10
Classifier: Programming Language :: Python :: 3.11
Classifier: Programming Language :: Python :: 3.12
Classifier: Programming Language :: Python :: 3.13
Classifier: Programming Language :: Python :: 3.14
Classifier: Topic :: Software Development :: Libraries :: Python Modules
Requires-Dist: chardet (>=4,<6)
Requires-Dist: charset-normalizer (>=3.2.0,<4.0.0)
Requires-Dist: codespell (==2.4.1)
Requires-Dist: gitpython (>=3.1.31,<4.0.0)
Requires-Dist: networkx (>=3.4.2,<4.0.0)
Requires-Dist: pontos (>=22.7,<26.0)
Requires-Dist: python-magic (>=0.4.25,<0.5.0)
Requires-Dist: validators (>=0.34.0,<0.35.0)
Project-URL: Homepage, https://github.com/greenbone/troubadix
Project-URL: Repository, https://github.com/greenbone/troubadix
